pairwiseprediction/__init__.py
pairwiseprediction/classifier.py
pairwiseprediction/combination.py
pairwiseprediction/interpolation.py
pairwiseprediction/optimized.py
pairwiseprediction-0.240311.7.dist-info/METADATA
pairwiseprediction-0.240311.7.dist-info/WHEEL
pairwiseprediction-0.240311.7.dist-info/RECORD
