Metadata-Version: 2.1
Name: pairwiseprediction
Version: 0.240311.7
Summary: Handle a regression problem inducing the model on pairs A,B of instances
Author: davips
Author-email: dpsabc@gmail.com
Requires-Python: >=3.10,<4.0
Classifier: Programming Language :: Python :: 3
Classifier: Programming Language :: Python :: 3.10
Classifier: Programming Language :: Python :: 3.11
Classifier: Programming Language :: Python :: 3.12
Requires-Dist: scikit-learn (>=1.3.2,<2.0.0)
